setup.py
vistascraper.py
vistascraper.egg-info/PKG-INFO
vistascraper.egg-info/SOURCES.txt
vistascraper.egg-info/dependency_links.txt
vistascraper.egg-info/entry_points.txt
vistascraper.egg-info/requires.txt
vistascraper.egg-info/top_level.txt