Metadata-Version: 1.0
Name: vistascraper
Version: 0.3
Summary: Interactive scraper for Vista database pages
Home-page: https://bitbucket.org/celynwalters/vistascraper/overview
Author: Celyn Walters
Author-email: celyn.walters@stfc.ac.uk
License: UNKNOWN
Platform: UNKNOWN
